{"cate":"cs.SI","year":2012,"paper_score":5237}
{"cate":"math.NT","year":2009,"paper_score":2407}
{"cate":"quant-ph","year":2007,"paper_score":4991}
{"cate":"cs.LO","year":2014,"paper_score":2015}
{"cate":"q-bio.NC","year":2014,"paper_score":787}
{"cate":"hep-lat","year":2011,"paper_score":6209}
{"cate":"cond-mat.soft","year":2015,"paper_score":2512}
{"cate":"cs.LG","year":2009,"paper_score":2152}
{"cate":"nucl-th","year":2008,"paper_score":6962}
{"cate":"cs.NE","year":2007,"paper_score":228}
{"cate":"cs.CE","year":2004,"paper_score":84}
{"cate":"cs.AI","year":2004,"paper_score":365}
{"cate":"cond-mat.quant-gas","year":2016,"paper_score":70}
{"cate":"physics.acc-ph","year":2005,"paper_score":16}
{"cate":"math.GR","year":2001,"paper_score":8}
{"cate":"math.NT","year":2000,"paper_score":35}
{"cate":"q-bio.QM","year":2017,"paper_score":3}
{"cate":"stat.ME","year":2004,"paper_score":24}
